py4ai/core/__init__.py
py4ai/core/_version.py
py4ai/core/py.typed
py4ai/core/config/__init__.py
py4ai/core/config/configurations.py
py4ai/core/logging/__init__.py
py4ai/core/tests/__init__.py
py4ai/core/tests/core.py
py4ai/core/types/__init__.py
py4ai/core/utils/__init__.py
py4ai/core/utils/cloud.py
py4ai/core/utils/decorators.py
py4ai/core/utils/dict.py
py4ai/core/utils/email.py
py4ai/core/utils/executors.py
py4ai/core/utils/fs.py
py4ai/core/utils/pandas.py
requirements/requirements.in
requirements/requirements_dev.in
py4ai_core-1.0.2.dist-info/LICENSE
py4ai_core-1.0.2.dist-info/METADATA
py4ai_core-1.0.2.dist-info/WHEEL
py4ai_core-1.0.2.dist-info/top_level.txt
py4ai_core-1.0.2.dist-info/RECORD
