Metadata-Version: 2.1
Name: py4ai-core
Version: 1.0.2
Summary: A Python library of data structures optimized for machine learning tasks
Author-email: Nicola Donelli <nicoladonelli87@gmail.com>, Enrico Deusebio <edeusebio85@gmail.com>
License: MIT
Project-URL: Homepage, https://github.com/NicolaDonelli/py4ai-core
Classifier: Programming Language :: Python :: 3
Classifier: License :: OSI Approved :: MIT License
Classifier: Operating System :: OS Independent
Requires-Python: >=3.8
License-File: LICENSE
Requires-Dist: cfg-load >=0.8
Requires-Dist: deprecated >=1.2.12
Requires-Dist: pandas >=1.0
Requires-Dist: pydantic >=1.9
Requires-Dist: scipy >=1.7.3
Requires-Dist: setuptools >=61.2
Requires-Dist: tomli >=2.0.1
Requires-Dist: typing-extensions >=4.0
Provides-Extra: dev
Requires-Dist: bandit[toml] >=1.7.4 ; extra == 'dev'
Requires-Dist: black >=21.12b0 ; extra == 'dev'
Requires-Dist: darglint >=1.8.1 ; extra == 'dev'
Requires-Dist: flake8 >=4.0.1 ; extra == 'dev'
Requires-Dist: flake8-docstrings >=1.6 ; extra == 'dev'
Requires-Dist: flake8-rst-docstrings >=0.2.5 ; extra == 'dev'
Requires-Dist: Flake8-pyproject >=1.1.0 ; extra == 'dev'
Requires-Dist: greenlet >=1.1.3 ; extra == 'dev'
Requires-Dist: isort >=5.10.1 ; extra == 'dev'
Requires-Dist: licensecheck <2023.2.0,>=2023.1.0 ; extra == 'dev'
Requires-Dist: m2r2 <0.3.3,>=0.3.2 ; extra == 'dev'
Requires-Dist: mypy >=0.910 ; extra == 'dev'
Requires-Dist: mypy-extensions >=0.4.3 ; extra == 'dev'
Requires-Dist: pip-tools >=7.3.0 ; extra == 'dev'
Requires-Dist: pytest >=6.2 ; extra == 'dev'
Requires-Dist: pytest-cov >=3.0 ; extra == 'dev'
Requires-Dist: recommonmark >=0.7 ; extra == 'dev'
Requires-Dist: Sphinx <6.0.0,>4.1 ; extra == 'dev'
Requires-Dist: sphinx-rtd-theme >=0.5 ; extra == 'dev'
Requires-Dist: twine >=3.8 ; extra == 'dev'
Requires-Dist: versioneer >=0.21 ; extra == 'dev'
